odoo8_addon_website_snippet_contact_form-8.0.1.0.0.99.dev38-py3.8-nspkg.pth
odoo_addons/website_snippet_contact_form/README.rst
odoo_addons/website_snippet_contact_form/__init__.py
odoo_addons/website_snippet_contact_form/__openerp__.py
odoo_addons/website_snippet_contact_form/controllers/__init__.py
odoo_addons/website_snippet_contact_form/controllers/main.py
odoo_addons/website_snippet_contact_form/i18n/af.po
odoo_addons/website_snippet_contact_form/i18n/ar.po
odoo_addons/website_snippet_contact_form/i18n/bg.po
odoo_addons/website_snippet_contact_form/i18n/ca.po
odoo_addons/website_snippet_contact_form/i18n/da.po
odoo_addons/website_snippet_contact_form/i18n/de.po
odoo_addons/website_snippet_contact_form/i18n/el.po
odoo_addons/website_snippet_contact_form/i18n/el_GR.po
odoo_addons/website_snippet_contact_form/i18n/es.po
odoo_addons/website_snippet_contact_form/i18n/es_CO.po
odoo_addons/website_snippet_contact_form/i18n/es_DO.po
odoo_addons/website_snippet_contact_form/i18n/es_EC.po
odoo_addons/website_snippet_contact_form/i18n/es_MX.po
odoo_addons/website_snippet_contact_form/i18n/es_PE.po
odoo_addons/website_snippet_contact_form/i18n/es_VE.po
odoo_addons/website_snippet_contact_form/i18n/et.po
odoo_addons/website_snippet_contact_form/i18n/eu.po
odoo_addons/website_snippet_contact_form/i18n/fa.po
odoo_addons/website_snippet_contact_form/i18n/fi.po
odoo_addons/website_snippet_contact_form/i18n/fr.po
odoo_addons/website_snippet_contact_form/i18n/he.po
odoo_addons/website_snippet_contact_form/i18n/hr.po
odoo_addons/website_snippet_contact_form/i18n/hu.po
odoo_addons/website_snippet_contact_form/i18n/id.po
odoo_addons/website_snippet_contact_form/i18n/it.po
odoo_addons/website_snippet_contact_form/i18n/ka.po
odoo_addons/website_snippet_contact_form/i18n/kab.po
odoo_addons/website_snippet_contact_form/i18n/ko.po
odoo_addons/website_snippet_contact_form/i18n/lv.po
odoo_addons/website_snippet_contact_form/i18n/mk.po
odoo_addons/website_snippet_contact_form/i18n/mn.po
odoo8_addon_website_snippet_contact_form-8.0.1.0.0.99.dev38.dist-info/METADATA
odoo8_addon_website_snippet_contact_form-8.0.1.0.0.99.dev38.dist-info/WHEEL
odoo8_addon_website_snippet_contact_form-8.0.1.0.0.99.dev38.dist-info/namespace_packages.txt
odoo8_addon_website_snippet_contact_form-8.0.1.0.0.99.dev38.dist-info/top_level.txt
odoo8_addon_website_snippet_contact_form-8.0.1.0.0.99.dev38.dist-info/RECORD
